ankur_scraper/__init__.py
ankur_scraper/_version.py
ankur_scraper/cli.py
ankur_scraper/dispatcher.py
ankur_scraper/logging_config.py
ankur_scraper/core/__init__.py
ankur_scraper/core/crawler.py
ankur_scraper/core/html_extractor.py
ankur_scraper/core/page_scraper.py
ankur_scraper/logs/error.log
ankur_scraper/logs/general.log
ankur_scraper/logs/info.log
ankur_scraper-0.1.4.dist-info/METADATA
ankur_scraper-0.1.4.dist-info/WHEEL
ankur_scraper-0.1.4.dist-info/entry_points.txt
ankur_scraper-0.1.4.dist-info/top_level.txt
ankur_scraper-0.1.4.dist-info/RECORD
