Metadata-Version: 2.4
Name: ankur_scraper
Version: 0.1.4
Summary: A robust website scraper that supports static and dynamic pages.
Author-email: Ankur Dev <Dev@ankursolutions.com>
Project-URL: Homepage, https://github.com/AnkurSolutions/ankur-scraper
Requires-Python: >=3.8
Requires-Dist: requests
Requires-Dist: beautifulsoup4
Requires-Dist: lxml
Requires-Dist: playwright
Requires-Dist: tldextract
Requires-Dist: rich
Requires-Dist: httpx
